pythonlib/__init__.py
pythonlib/mymodule.py
mypackage01-0.1.dist-info/METADATA
mypackage01-0.1.dist-info/WHEEL
mypackage01-0.1.dist-info/top_level.txt
mypackage01-0.1.dist-info/RECORD
