Metadata-Version: 2.1
Name: mypackage01
Version: 0.1
Summary: My Python package
Author: sai kumar sapa
Author-email: saikumarsapa@gmail.com
